{
  "version_formato": "1.7",
  "aplicacion": {
    "nombre": "Generador de Horarios Escolares",
    "version": "1.4.1"
  },
  "centro": {
    "nombre": "CEE de ejemplo",
    "tipo": "CEE",
    "curso_academico": "2026-2027",
    "descripcion": "Ejemplo sintético sin datos reales."
  },
  "dias": [
    {
      "id": "dia_1",
      "nombre": "Lunes",
      "orden": 1
    },
    {
      "id": "dia_2",
      "nombre": "Martes",
      "orden": 2
    },
    {
      "id": "dia_3",
      "nombre": "Miércoles",
      "orden": 3
    },
    {
      "id": "dia_4",
      "nombre": "Jueves",
      "orden": 4
    },
    {
      "id": "dia_5",
      "nombre": "Viernes",
      "orden": 5
    }
  ],
  "tramos": [
    {
      "id": "tramo_1",
      "nombre": "1.ª hora",
      "orden": 1,
      "inicio": "08:50",
      "fin": "09:40",
      "duracion_minutos": 50,
      "tipo_tramo": "Lectivo",
      "admite_clase": true,
      "admite_servicios": false,
      "computa_permanencia": true
    },
    {
      "id": "tramo_2",
      "nombre": "2.ª hora",
      "orden": 2,
      "inicio": "09:40",
      "fin": "10:30",
      "duracion_minutos": 50,
      "tipo_tramo": "Lectivo",
      "admite_clase": true,
      "admite_servicios": false,
      "computa_permanencia": true
    },
    {
      "id": "tramo_3",
      "nombre": "3.ª hora",
      "orden": 3,
      "inicio": "11:00",
      "fin": "11:50",
      "duracion_minutos": 50,
      "tipo_tramo": "Lectivo",
      "admite_clase": true,
      "admite_servicios": false,
      "computa_permanencia": true
    },
    {
      "id": "tramo_4",
      "nombre": "4.ª hora",
      "orden": 4,
      "inicio": "11:50",
      "fin": "12:40",
      "duracion_minutos": 50,
      "tipo_tramo": "Lectivo",
      "admite_clase": true,
      "admite_servicios": false,
      "computa_permanencia": true
    },
    {
      "id": "tramo_5",
      "nombre": "5.ª hora",
      "orden": 5,
      "inicio": "12:40",
      "fin": "13:30",
      "duracion_minutos": 50,
      "tipo_tramo": "Lectivo",
      "admite_clase": true,
      "admite_servicios": false,
      "computa_permanencia": true
    },
    {
      "id": "tramo_6",
      "nombre": "6.ª hora",
      "orden": 6,
      "inicio": "13:00",
      "fin": "13:50",
      "duracion_minutos": 50,
      "tipo_tramo": "Lectivo",
      "admite_clase": true,
      "admite_servicios": false,
      "computa_permanencia": true
    }
  ],
  "personas": [
    {
      "id": "persona_x2t9h_kuv30wk",
      "nombre": "Ana García",
      "departamento": "Departamento",
      "horas_maximas": 25,
      "observaciones": "",
      "disponibilidad": {
        "dia_1__tramo_1": true,
        "dia_1__tramo_2": true,
        "dia_1__tramo_3": true,
        "dia_1__tramo_4": true,
        "dia_1__tramo_5": true,
        "dia_1__tramo_6": true,
        "dia_2__tramo_1": true,
        "dia_2__tramo_2": true,
        "dia_2__tramo_3": true,
        "dia_2__tramo_4": true,
        "dia_2__tramo_5": true,
        "dia_2__tramo_6": true,
        "dia_3__tramo_1": true,
        "dia_3__tramo_2": true,
        "dia_3__tramo_3": true,
        "dia_3__tramo_4": true,
        "dia_3__tramo_5": true,
        "dia_3__tramo_6": true,
        "dia_4__tramo_1": true,
        "dia_4__tramo_2": true,
        "dia_4__tramo_3": true,
        "dia_4__tramo_4": true,
        "dia_4__tramo_5": true,
        "dia_4__tramo_6": true,
        "dia_5__tramo_1": true,
        "dia_5__tramo_2": true,
        "dia_5__tramo_3": true,
        "dia_5__tramo_4": true,
        "dia_5__tramo_5": true,
        "dia_5__tramo_6": true
      },
      "horas_lectivas_objetivo": 0,
      "horas_dc_objetivo": 0,
      "horas_permanencia_objetivo": 0
    },
    {
      "id": "persona_x2t9h_l9gh2xx",
      "nombre": "Luis Pérez",
      "departamento": "Ámbito / especialidad",
      "horas_maximas": 25,
      "observaciones": "",
      "disponibilidad": {
        "dia_1__tramo_1": true,
        "dia_1__tramo_2": true,
        "dia_1__tramo_3": true,
        "dia_1__tramo_4": true,
        "dia_1__tramo_5": true,
        "dia_1__tramo_6": true,
        "dia_2__tramo_1": true,
        "dia_2__tramo_2": true,
        "dia_2__tramo_3": true,
        "dia_2__tramo_4": true,
        "dia_2__tramo_5": true,
        "dia_2__tramo_6": true,
        "dia_3__tramo_1": true,
        "dia_3__tramo_2": true,
        "dia_3__tramo_3": true,
        "dia_3__tramo_4": true,
        "dia_3__tramo_5": true,
        "dia_3__tramo_6": true,
        "dia_4__tramo_1": true,
        "dia_4__tramo_2": true,
        "dia_4__tramo_3": true,
        "dia_4__tramo_4": true,
        "dia_4__tramo_5": true,
        "dia_4__tramo_6": true,
        "dia_5__tramo_1": true,
        "dia_5__tramo_2": true,
        "dia_5__tramo_3": true,
        "dia_5__tramo_4": true,
        "dia_5__tramo_5": true,
        "dia_5__tramo_6": true
      },
      "horas_lectivas_objetivo": 0,
      "horas_dc_objetivo": 0,
      "horas_permanencia_objetivo": 0
    },
    {
      "id": "persona_x2t9h_6bvkj3g",
      "nombre": "María López",
      "departamento": "Departamento",
      "horas_maximas": 25,
      "observaciones": "",
      "disponibilidad": {
        "dia_1__tramo_1": true,
        "dia_1__tramo_2": true,
        "dia_1__tramo_3": true,
        "dia_1__tramo_4": true,
        "dia_1__tramo_5": true,
        "dia_1__tramo_6": true,
        "dia_2__tramo_1": true,
        "dia_2__tramo_2": true,
        "dia_2__tramo_3": true,
        "dia_2__tramo_4": true,
        "dia_2__tramo_5": true,
        "dia_2__tramo_6": true,
        "dia_3__tramo_1": true,
        "dia_3__tramo_2": true,
        "dia_3__tramo_3": true,
        "dia_3__tramo_4": true,
        "dia_3__tramo_5": true,
        "dia_3__tramo_6": true,
        "dia_4__tramo_1": true,
        "dia_4__tramo_2": true,
        "dia_4__tramo_3": true,
        "dia_4__tramo_4": true,
        "dia_4__tramo_5": true,
        "dia_4__tramo_6": true,
        "dia_5__tramo_1": true,
        "dia_5__tramo_2": true,
        "dia_5__tramo_3": true,
        "dia_5__tramo_4": true,
        "dia_5__tramo_5": true,
        "dia_5__tramo_6": true
      },
      "horas_lectivas_objetivo": 0,
      "horas_dc_objetivo": 0,
      "horas_permanencia_objetivo": 0
    },
    {
      "id": "persona_x2t9h_c75nigz",
      "nombre": "Carlos Santos",
      "departamento": "Ámbito / especialidad",
      "horas_maximas": 25,
      "observaciones": "",
      "disponibilidad": {
        "dia_1__tramo_1": true,
        "dia_1__tramo_2": true,
        "dia_1__tramo_3": true,
        "dia_1__tramo_4": true,
        "dia_1__tramo_5": true,
        "dia_1__tramo_6": true,
        "dia_2__tramo_1": true,
        "dia_2__tramo_2": true,
        "dia_2__tramo_3": true,
        "dia_2__tramo_4": true,
        "dia_2__tramo_5": true,
        "dia_2__tramo_6": true,
        "dia_3__tramo_1": true,
        "dia_3__tramo_2": true,
        "dia_3__tramo_3": true,
        "dia_3__tramo_4": true,
        "dia_3__tramo_5": true,
        "dia_3__tramo_6": true,
        "dia_4__tramo_1": true,
        "dia_4__tramo_2": true,
        "dia_4__tramo_3": true,
        "dia_4__tramo_4": true,
        "dia_4__tramo_5": true,
        "dia_4__tramo_6": true,
        "dia_5__tramo_1": true,
        "dia_5__tramo_2": true,
        "dia_5__tramo_3": true,
        "dia_5__tramo_4": true,
        "dia_5__tramo_5": true,
        "dia_5__tramo_6": true
      },
      "horas_lectivas_objetivo": 0,
      "horas_dc_objetivo": 0,
      "horas_permanencia_objetivo": 0
    }
  ],
  "grupos": [
    {
      "id": "grupo_x2t9h_kfi83dq",
      "nombre": "Unidad 1",
      "ensenanza": "",
      "nivel": "",
      "observaciones": "",
      "grupo_matriz_id": "",
      "tipo_agrupamiento": "Grupo",
      "permite_paralelo_con_matriz": false
    },
    {
      "id": "grupo_x2t9h_7qkq6uo",
      "nombre": "Unidad 2",
      "ensenanza": "",
      "nivel": "",
      "observaciones": "",
      "grupo_matriz_id": "",
      "tipo_agrupamiento": "Grupo",
      "permite_paralelo_con_matriz": false
    },
    {
      "id": "grupo_x2t9h_vi6nboz",
      "nombre": "Grupo apoyo comunicación",
      "ensenanza": "",
      "nivel": "",
      "observaciones": "",
      "grupo_matriz_id": "",
      "tipo_agrupamiento": "Grupo",
      "permite_paralelo_con_matriz": false
    }
  ],
  "espacios": [
    {
      "id": "espacio_x2t9h_c9c5tdp",
      "nombre": "Aula unidad 1",
      "tipo": "Aula ordinaria",
      "capacidad": "",
      "observaciones": "",
      "disponibilidad": {
        "dia_1__tramo_1": true,
        "dia_1__tramo_2": true,
        "dia_1__tramo_3": true,
        "dia_1__tramo_4": true,
        "dia_1__tramo_5": true,
        "dia_1__tramo_6": true,
        "dia_2__tramo_1": true,
        "dia_2__tramo_2": true,
        "dia_2__tramo_3": true,
        "dia_2__tramo_4": true,
        "dia_2__tramo_5": true,
        "dia_2__tramo_6": true,
        "dia_3__tramo_1": true,
        "dia_3__tramo_2": true,
        "dia_3__tramo_3": true,
        "dia_3__tramo_4": true,
        "dia_3__tramo_5": true,
        "dia_3__tramo_6": true,
        "dia_4__tramo_1": true,
        "dia_4__tramo_2": true,
        "dia_4__tramo_3": true,
        "dia_4__tramo_4": true,
        "dia_4__tramo_5": true,
        "dia_4__tramo_6": true,
        "dia_5__tramo_1": true,
        "dia_5__tramo_2": true,
        "dia_5__tramo_3": true,
        "dia_5__tramo_4": true,
        "dia_5__tramo_5": true,
        "dia_5__tramo_6": true
      }
    },
    {
      "id": "espacio_x2t9h_jg5ihcb",
      "nombre": "Aula unidad 2",
      "tipo": "Aula ordinaria",
      "capacidad": "",
      "observaciones": "",
      "disponibilidad": {
        "dia_1__tramo_1": true,
        "dia_1__tramo_2": true,
        "dia_1__tramo_3": true,
        "dia_1__tramo_4": true,
        "dia_1__tramo_5": true,
        "dia_1__tramo_6": true,
        "dia_2__tramo_1": true,
        "dia_2__tramo_2": true,
        "dia_2__tramo_3": true,
        "dia_2__tramo_4": true,
        "dia_2__tramo_5": true,
        "dia_2__tramo_6": true,
        "dia_3__tramo_1": true,
        "dia_3__tramo_2": true,
        "dia_3__tramo_3": true,
        "dia_3__tramo_4": true,
        "dia_3__tramo_5": true,
        "dia_3__tramo_6": true,
        "dia_4__tramo_1": true,
        "dia_4__tramo_2": true,
        "dia_4__tramo_3": true,
        "dia_4__tramo_4": true,
        "dia_4__tramo_5": true,
        "dia_4__tramo_6": true,
        "dia_5__tramo_1": true,
        "dia_5__tramo_2": true,
        "dia_5__tramo_3": true,
        "dia_5__tramo_4": true,
        "dia_5__tramo_5": true,
        "dia_5__tramo_6": true
      }
    },
    {
      "id": "espacio_x2t9h_kzj08e8",
      "nombre": "Sala atención específica",
      "tipo": "Aula ordinaria",
      "capacidad": "",
      "observaciones": "",
      "disponibilidad": {
        "dia_1__tramo_1": true,
        "dia_1__tramo_2": true,
        "dia_1__tramo_3": true,
        "dia_1__tramo_4": true,
        "dia_1__tramo_5": true,
        "dia_1__tramo_6": true,
        "dia_2__tramo_1": true,
        "dia_2__tramo_2": true,
        "dia_2__tramo_3": true,
        "dia_2__tramo_4": true,
        "dia_2__tramo_5": true,
        "dia_2__tramo_6": true,
        "dia_3__tramo_1": true,
        "dia_3__tramo_2": true,
        "dia_3__tramo_3": true,
        "dia_3__tramo_4": true,
        "dia_3__tramo_5": true,
        "dia_3__tramo_6": true,
        "dia_4__tramo_1": true,
        "dia_4__tramo_2": true,
        "dia_4__tramo_3": true,
        "dia_4__tramo_4": true,
        "dia_4__tramo_5": true,
        "dia_4__tramo_6": true,
        "dia_5__tramo_1": true,
        "dia_5__tramo_2": true,
        "dia_5__tramo_3": true,
        "dia_5__tramo_4": true,
        "dia_5__tramo_5": true,
        "dia_5__tramo_6": true
      }
    },
    {
      "id": "espacio_x2t9h_oi54shi",
      "nombre": "Gimnasio terapéutico",
      "tipo": "Aula ordinaria",
      "capacidad": "",
      "observaciones": "",
      "disponibilidad": {
        "dia_1__tramo_1": true,
        "dia_1__tramo_2": true,
        "dia_1__tramo_3": true,
        "dia_1__tramo_4": true,
        "dia_1__tramo_5": true,
        "dia_1__tramo_6": true,
        "dia_2__tramo_1": true,
        "dia_2__tramo_2": true,
        "dia_2__tramo_3": true,
        "dia_2__tramo_4": true,
        "dia_2__tramo_5": true,
        "dia_2__tramo_6": true,
        "dia_3__tramo_1": true,
        "dia_3__tramo_2": true,
        "dia_3__tramo_3": true,
        "dia_3__tramo_4": true,
        "dia_3__tramo_5": true,
        "dia_3__tramo_6": true,
        "dia_4__tramo_1": true,
        "dia_4__tramo_2": true,
        "dia_4__tramo_3": true,
        "dia_4__tramo_4": true,
        "dia_4__tramo_5": true,
        "dia_4__tramo_6": true,
        "dia_5__tramo_1": true,
        "dia_5__tramo_2": true,
        "dia_5__tramo_3": true,
        "dia_5__tramo_4": true,
        "dia_5__tramo_5": true,
        "dia_5__tramo_6": true
      }
    }
  ],
  "actividades": [
    {
      "id": "actividad_x2t9h_u42hee7",
      "nombre": "Ámbito de autonomía personal",
      "tipo": "Ámbito",
      "grupo_id": "grupo_x2t9h_kfi83dq",
      "persona_id": "persona_x2t9h_kuv30wk",
      "espacio_id": "espacio_x2t9h_c9c5tdp",
      "sesiones_semanales": 4,
      "duracion_tramos": 1,
      "requiere_espacio": true,
      "condiciones": {
        "dias_prohibidos": [],
        "tramos_prohibidos": [],
        "huecos_prohibidos": [],
        "dias_preferidos": [],
        "tramos_preferidos": [],
        "una_sesion_por_dia": false,
        "prohibir_ultima_hora": true
      },
      "observaciones": "",
      "clasificacion_horaria": "Lectiva",
      "requiere_grupo": true,
      "docentes_acompanantes_ids": [],
      "docentes_necesarios": 1,
      "computa_lectivo": true,
      "computa_no_lectivo": false
    },
    {
      "id": "actividad_x2t9h_ad95wjz",
      "nombre": "Atención específica AL",
      "tipo": "Atención específica",
      "grupo_id": "grupo_x2t9h_vi6nboz",
      "persona_id": "persona_x2t9h_l9gh2xx",
      "espacio_id": "espacio_x2t9h_kzj08e8",
      "sesiones_semanales": 3,
      "duracion_tramos": 1,
      "requiere_espacio": true,
      "condiciones": {
        "dias_prohibidos": [],
        "tramos_prohibidos": [],
        "huecos_prohibidos": [],
        "dias_preferidos": [],
        "tramos_preferidos": [],
        "una_sesion_por_dia": true,
        "prohibir_ultima_hora": false
      },
      "observaciones": "",
      "clasificacion_horaria": "Lectiva",
      "requiere_grupo": true,
      "docentes_acompanantes_ids": [],
      "docentes_necesarios": 1,
      "computa_lectivo": true,
      "computa_no_lectivo": false
    },
    {
      "id": "actividad_x2t9h_oqse1qq",
      "nombre": "Psicomotricidad",
      "tipo": "Apoyo",
      "grupo_id": "grupo_x2t9h_7qkq6uo",
      "persona_id": "persona_x2t9h_6bvkj3g",
      "espacio_id": "espacio_x2t9h_oi54shi",
      "sesiones_semanales": 2,
      "duracion_tramos": 1,
      "requiere_espacio": true,
      "condiciones": {
        "dias_prohibidos": [],
        "tramos_prohibidos": [],
        "huecos_prohibidos": [],
        "dias_preferidos": [],
        "tramos_preferidos": [],
        "una_sesion_por_dia": false,
        "prohibir_ultima_hora": false
      },
      "observaciones": "",
      "clasificacion_horaria": "Lectiva",
      "requiere_grupo": true,
      "docentes_acompanantes_ids": [],
      "docentes_necesarios": 1,
      "computa_lectivo": true,
      "computa_no_lectivo": false
    },
    {
      "id": "actividad_x2t9h_sy1fn2y",
      "nombre": "Tutoría y coordinación",
      "tipo": "Tutoría",
      "grupo_id": "grupo_x2t9h_kfi83dq",
      "persona_id": "persona_x2t9h_c75nigz",
      "espacio_id": "espacio_x2t9h_c9c5tdp",
      "sesiones_semanales": 1,
      "duracion_tramos": 1,
      "requiere_espacio": true,
      "condiciones": {
        "dias_prohibidos": [],
        "tramos_prohibidos": [],
        "huecos_prohibidos": [],
        "dias_preferidos": [],
        "tramos_preferidos": [],
        "una_sesion_por_dia": false,
        "prohibir_ultima_hora": false
      },
      "observaciones": "",
      "clasificacion_horaria": "Lectiva",
      "requiere_grupo": true,
      "docentes_acompanantes_ids": [],
      "docentes_necesarios": 1,
      "computa_lectivo": true,
      "computa_no_lectivo": false
    }
  ],
  "horario": [],
  "preferencias": {
    "repartir_actividad_en_dias": true,
    "evitar_ultima_hora": false,
    "compactar_profesorado": false,
    "minimizar_cambios_espacio": true,
    "priorizar_tramos_preferidos": true
  },
  "historial": [],
  "metadatos": {
    "creado": "2026-06-19T12:40:32.933Z",
    "modificado": "2026-06-19T00:00:00.000Z",
    "origen": "nuevo"
  },
  "gestion_diaria": {
    "ausencias": [],
    "coberturas": [],
    "incidencias": []
  }
}